sufficient/__about__.py
sufficient/__init__.py
sufficient/frames/__init__.py
sufficient/frames/farcaster_client.py
sufficient/frames/frame_app_loader.py
sufficient/frames/frame_app_runner.py
sufficient/frames/frame_context.py
sufficient-0.1.3.dist-info/METADATA
sufficient-0.1.3.dist-info/WHEEL
sufficient-0.1.3.dist-info/licenses/LICENSE.txt
sufficient-0.1.3.dist-info/RECORD
