Metadata-Version: 2.1
Name: sufficient
Version: 0.1.3
Summary: A framework for creating Frame apps in an intuitive and declarative manner
Project-URL: Documentation, https://github.com/briceyan/sufficient-py#readme
Project-URL: Issues, https://github.com/briceyan/sufficient-py/issues
Project-URL: Source, https://github.com/briceyan/sufficient-py
Author-email: Brice Yan <briceyan3.0@gmail.com>
License-Expression: MIT
License-File: LICENSE.txt
Classifier: Development Status :: 4 - Beta
Classifier: Programming Language :: Python
Classifier: Programming Language :: Python :: 3.8
Classifier: Programming Language :: Python :: 3.9
Classifier: Programming Language :: Python :: 3.10
Classifier: Programming Language :: Python :: 3.11
Classifier: Programming Language :: Python :: 3.12
Classifier: Programming Language :: Python :: Implementation :: CPython
Classifier: Programming Language :: Python :: Implementation :: PyPy
Requires-Python: >=3.8
Requires-Dist: chevron
Requires-Dist: inflection
Requires-Dist: jinja2
Requires-Dist: requests
